cobralib/__init__.py
cobralib/db.py
cobralib/io.py
cobralib-0.2.1.dist-info/LICENSE
cobralib-0.2.1.dist-info/METADATA
cobralib-0.2.1.dist-info/WHEEL
cobralib-0.2.1.dist-info/RECORD
