Metadata-Version: 2.1
Name: cobralib
Version: 0.2.1
Summary: A utilities module that contains classes and functions that simplify interfaces with files and databases.
Author: Jon Webb
Author-email: webbja123@gmail.com
Requires-Python: >=3.11,<4.0
Classifier: Programming Language :: Python :: 3
Classifier: Programming Language :: Python :: 3.11
Provides-Extra: mysql
Provides-Extra: postgresql
Requires-Dist: mysql-connector-python[mysql] (>=8.1.0,<9.0.0) ; extra == "mysql"
Requires-Dist: numpy (>=1.25.1,<2.0.0)
Requires-Dist: pandas (>=2.0.3,<3.0.0)
Requires-Dist: pdfplumber (>=0.10.2,<0.11.0)
Requires-Dist: pygresql[postgresql] (>=5.2.4,<6.0.0) ; extra == "postgresql"
Requires-Dist: pyodbc (>=4.0.39,<5.0.0)
Requires-Dist: pyyaml (>=6.0,<7.0)
Requires-Dist: sphinx-rtd-theme (>=1.3.0,<2.0.0)
Requires-Dist: xmltodict (>=0.13.0,<0.14.0)
Project-URL: Documentation, https://cobralib.readthedocs.io/en/latest/index.html
Project-URL: Homepage, https://github.com/Jon-Webb-79/cobralib
